MANIFEST.in
requirements.txt
setup.py
estat/__init__.py
estat/e_Stat_API_Adaptor.py
estat/estat.py
estat.egg-info/PKG-INFO
estat.egg-info/SOURCES.txt
estat.egg-info/dependency_links.txt
estat.egg-info/entry_points.txt
estat.egg-info/requires.txt
estat.egg-info/top_level.txt