Metadata-Version: 1.1
Name: estat
Version: 1.2.0
Summary: Download data from Japanese Government Statistics and save it as CSV format files
Home-page: https://github.com/kenbunji/estat
Author: kenbunji
Author-email: kenbunji@gmail.com
License: MIT
Platform: UNKNOWN
Classifier: Programming Language :: Python :: 2
Classifier: Programming Language :: Python :: 2.7
Classifier: Programming Language :: Python :: 3
Classifier: Programming Language :: Python :: 3.3
Classifier: Programming Language :: Python :: 3.4
Classifier: Programming Language :: Python :: 3.5
Classifier: Programming Language :: Python :: 3.6
Classifier: Programming Language :: Python :: 3.7
Classifier: License :: OSI Approved :: MIT License
